cfscrape/__init__.py
cfscrape/user_agents.json
cfscrape/user_agents.py
cfscrape-2.1.0.dist-info/LICENSE
cfscrape-2.1.0.dist-info/METADATA
cfscrape-2.1.0.dist-info/WHEEL
cfscrape-2.1.0.dist-info/top_level.txt
cfscrape-2.1.0.dist-info/RECORD
