Metadata-Version: 2.1
Name: cfscrape
Version: 2.1.0
Summary: A simple Python module to bypass Cloudflare's anti-bot page. See https://github.com/Anorov/cloudflare-scrape for more information.
Home-page: https://github.com/Anorov/cloudflare-scrape
Author: Anorov
Author-email: anorov.vorona@gmail.com
License: UNKNOWN
Keywords: cloudflare,scraping
Platform: UNKNOWN
Requires-Dist: requests (>=2.6.1)
